chocopy/__init__.py
chocopy/app.py
chocopy/exceptions.py
chocopy/get_information.py
chocopy/response.py
test/__init__.py
test/run.py
ChocoPY-0.1.6.dist-info/LICENSE
ChocoPY-0.1.6.dist-info/METADATA
ChocoPY-0.1.6.dist-info/WHEEL
ChocoPY-0.1.6.dist-info/top_level.txt
ChocoPY-0.1.6.dist-info/RECORD
