Metadata-Version: 2.1
Name: ChocoPY
Version: 0.1.6
Summary: Simple and easy development tool for create chat bot
Home-page: UNKNOWN
Author: MallyCrip
Author-email: pycon@kakao.com
License: UNKNOWN
Keywords: api,chat_bot
Platform: UNKNOWN
Classifier: Programming Language :: Python :: 3.6
Requires-Python: >=3
Requires-Dist: flask
